[
  {
    "product_name": "Crystal Clawz Rubber Base Gel",
    "category": "Nail base gel",
    "short_description": "A flexible rubber base gel for nail technicians who want a smooth base before colour or overlay work.",
    "key_benefits": [
      "Helps create a neat, even-looking base",
      "Useful for structured gel manicures",
      "Works well for short-form product education videos"
    ],
    "target_customer": "South African nail technicians and salon owners",
    "video_angle": "Show how a smooth base helps the colour application look cleaner and more professional.",
    "call_to_action": "Shop Crystal Clawz Rubber Base Gel and upgrade your next set."
  },
  {
    "product_name": "Crystal Clawz Rocket Sandwich Forms",
    "category": "Nail extension forms",
    "short_description": "Reusable-style nail forms designed to help nail technicians shape extensions with more control.",
    "key_benefits": [
      "Helps guide extension shape",
      "Supports cleaner product placement",
      "Good for quick demo and before-and-after content"
    ],
    "target_customer": "Nail technicians who create gel or acrylic extensions",
    "video_angle": "Demonstrate how forms help build a cleaner extension shape without over-explaining the process.",
    "call_to_action": "Try Rocket Sandwich Forms for your next extension set."
  },
  {
    "product_name": "Crystal Clawz Gel Polish",
    "category": "Gel polish",
    "short_description": "Salon gel polish for nail technicians who need polished colour content and product-focused reels.",
    "key_benefits": [
      "Creates a glossy salon-style finish",
      "Easy to feature in colour swatch videos",
      "Useful for service menus, reels, and Shopify product clips"
    ],
    "target_customer": "Nail technicians, salon owners, and nail product buyers",
    "video_angle": "Show a simple colour reveal with a close-up application and final glossy finish.",
    "call_to_action": "Browse Crystal Clawz Gel Polish shades and choose your next salon colour."
  }
]
